skodaconnect/__init__.py
skodaconnect/__version__.py
skodaconnect/connection.py
skodaconnect/const.py
skodaconnect/dashboard.py
skodaconnect/exceptions.py
skodaconnect/utilities.py
skodaconnect/vehicle.py
skodaconnect-1.3.11.dist-info/LICENSE
skodaconnect-1.3.11.dist-info/WHEEL
skodaconnect-1.3.11.dist-info/METADATA
skodaconnect-1.3.11.dist-info/RECORD
