Metadata-Version: 2.1
Name: skodaconnect
Version: 1.3.11
Summary: skodaconnect - A Python 3 library for interacting with Skoda Connect and Smartlink services.
Author-email: FarFar <faekie@hotmail.com>, dvx76 <fabrice.devaux@gmail.com>, WebSpider <bacardicoke@gmail.com>
Requires-Python: >=3.11
Classifier: License :: OSI Approved :: Apache Software License
Classifier: Development Status :: 4 - Beta
Classifier: Operating System :: POSIX
Classifier: Programming Language :: Python :: 3
Requires-Dist: aiohttp
Requires-Dist: beautifulsoup4
Requires-Dist: cryptography
Requires-Dist: lxml
Requires-Dist: pyjwt
Project-URL: Bug Tracker, https://github.com/skodaconnect/skodaconnect/issues
Project-URL: Homepage, https://github.com/skodaconnect
Project-URL: Repository, https://github.com/skodaconnect/skodaconnect.git
